.coveragerc
.flake8
.pylintrc
CHANGES.rst
MANIFEST.in
README.rst
setup.cfg
setup.py
tox.ini
atests/test_crl_doc_generate_rst.py
atests/expected_alldoc/sphinxdocs/builtin_index.rst
atests/expected_alldoc/sphinxdocs/crl_api_index.rst
atests/expected_alldoc/sphinxdocs/crl_index.rst
atests/expected_alldoc/sphinxdocs/builtin/BuiltIn.rst
atests/expected_alldoc/sphinxdocs/builtin/Collections.rst
atests/expected_alldoc/sphinxdocs/builtin/DateTime.rst
atests/expected_alldoc/sphinxdocs/builtin/Easter.rst
atests/expected_alldoc/sphinxdocs/builtin/OperatingSystem.rst
atests/expected_alldoc/sphinxdocs/builtin/Process.rst
atests/expected_alldoc/sphinxdocs/builtin/Reserved.rst
atests/expected_alldoc/sphinxdocs/builtin/Screenshot.rst
atests/expected_alldoc/sphinxdocs/builtin/String.rst
atests/expected_alldoc/sphinxdocs/builtin/Telnet.rst
atests/expected_alldoc/sphinxdocs/builtin/XML.rst
atests/expected_alldoc/sphinxdocs/crl/crl.examplelib.examplelib.Example.rst
atests/expected_alldoc/sphinxdocs/crl/crl.examplelib.examplelib.rst
atests/expected_alldoc/sphinxdocs/crl_api/modules.rst
atests/expected_alldoc/sphinxdocs/crl_api/tmpsrc.crl.examplelib.rst
atests/expected_builtindoc/sphinxdocs/builtin_index.rst
atests/expected_builtindoc/sphinxdocs/builtin/BuiltIn.rst
atests/expected_builtindoc/sphinxdocs/builtin/Collections.rst
atests/expected_builtindoc/sphinxdocs/builtin/DateTime.rst
atests/expected_builtindoc/sphinxdocs/builtin/Easter.rst
atests/expected_builtindoc/sphinxdocs/builtin/OperatingSystem.rst
atests/expected_builtindoc/sphinxdocs/builtin/Process.rst
atests/expected_builtindoc/sphinxdocs/builtin/Reserved.rst
atests/expected_builtindoc/sphinxdocs/builtin/Screenshot.rst
atests/expected_builtindoc/sphinxdocs/builtin/String.rst
atests/expected_builtindoc/sphinxdocs/builtin/Telnet.rst
atests/expected_builtindoc/sphinxdocs/builtin/XML.rst
atests/expected_crldoc/sphinxdocs/crl_index.rst
atests/expected_crldoc/sphinxdocs/crl/crl.examplelib.examplelib.Example.rst
src/crl.doc.egg-info/PKG-INFO
src/crl.doc.egg-info/SOURCES.txt
src/crl.doc.egg-info/dependency_links.txt
src/crl.doc.egg-info/entry_points.txt
src/crl.doc.egg-info/namespace_packages.txt
src/crl.doc.egg-info/requires.txt
src/crl.doc.egg-info/top_level.txt
