Metadata-Version: 1.2
Name: crl.doc
Version: 2.0.1
Summary: Documenation tools for Common Robot Libraries
Home-page: https://github.com/nokia/crl-doc
Author: Petri Huovinen
Author-email: petri.huovinen@nokia.com
License: BSD-3-Clause
Keywords: robotframework documentation
Platform: UNKNOWN
Classifier: Intended Audience :: Developers
Classifier: License :: OSI Approved :: BSD License
Classifier: Programming Language :: Python :: 3
Classifier: Programming Language :: Python :: 3.6
Classifier: Programming Language :: Python :: 3.7
Classifier: Topic :: Documentation :: Sphinx
Classifier: Environment :: Console
Classifier: Framework :: Robot Framework
Requires-Python: >=3.6.*
